EventStudySuite/__init__.py
EventStudySuite/core/__init__.py
EventStudySuite/core/es_base.py
EventStudySuite/error/__init__.py
EventStudySuite/model/MarketModel.py
EventStudySuite/model/__init__.py
EventStudySuite/utils/__init__.py
EventStudySuite/utils/boost_up.py
EventStudySuite/utils/cached_property.py
EventStudySuite/utils/chunk.py
EventStudySuite/utils/file_cache.py
EventStudySuite/utils/lazy_load.py
EventStudySuite/utils/o_server.py
EventStudySuite/utils/parse_rfc_1738_args.py
EventStudySuite/utils/uuid_generator.py
test/__init__.py
test/test_model.py
EventStudySuite-0.1.3.1.dist-info/METADATA
EventStudySuite-0.1.3.1.dist-info/WHEEL
EventStudySuite-0.1.3.1.dist-info/top_level.txt
EventStudySuite-0.1.3.1.dist-info/RECORD
