Metadata-Version: 2.1
Name: EventStudySuite
Version: 0.1.3.1
Summary: a event study tool
Home-page: http://www.github.com/sn0wfree/EventStudySuite
Author: sn0wfree
Author-email: snowfreedom0815@gmail.com
License: MIT Licence
Keywords: Event Study,analysis
Platform: UNKNOWN
